parsigs/__init__.py
parsigs/parse_sig_api.py
parsigs/resources/drug_names.txt
parsigs-1.0.0b0.dist-info/METADATA
parsigs-1.0.0b0.dist-info/WHEEL
parsigs-1.0.0b0.dist-info/licenses/LICENSE
parsigs-1.0.0b0.dist-info/RECORD
