Metadata-Version: 2.1
Name: parsigs
Version: 1.0.0b0
Summary: The private, smart and easy Sig (Dosage Instructions) text-parser
Project-URL: Homepage, https://github.com/royashcenazi/parsigs
Project-URL: Bug Tracker, https://github.com/royashcenazi/parsigs/issues
Author-email: Roy Ashcenazi <royashcenazi@gmail.com>
License-File: LICENSE
Requires-Dist: inflect
Requires-Dist: pyspellchecker<=0.5.5
Requires-Dist: spacy<4.0,>=3.0
Requires-Dist: word2number
